{
  "entities": [
    {
      "components": {
        "Name": {
          "name": "Main Camera"
        },
        "Camera": {
          "fov_y_radians": 1.0472,
          "aspect_ratio": 1.7778,
          "z_near": 1.0,
          "z_far": 100000000.0,
          "projection_mode": "Perspective",
          "use_logarithmic_depth": true
        },
        "WorldTransform": {
          "position": [9999995.0, 5.0, 10.0],
          "rotation": [0.0, 0.0, 0.0, 1.0],
          "scale": [1.0, 1.0, 1.0]
        }
      }
    },
    {
      "components": {
        "Name": {
          "name": "Cube at 10 Million Units"
        },
        "MeshId": {
          "0": "Cube"
        },
        "Material": {
          "color": [1.0, 0.0, 0.0, 1.0]
        },
        "WorldTransform": {
          "position": [10000000.0, 0.0, 0.0],
          "rotation": [0.0, 0.0, 0.0, 1.0],
          "scale": [5.0, 5.0, 5.0]
        }
      }
    },
    {
      "components": {
        "Name": {
          "name": "Reference Sphere Near Camera"
        },
        "MeshId": {
          "0": "Sphere"
        },
        "Material": {
          "color": [0.0, 1.0, 0.0, 1.0]
        },
        "WorldTransform": {
          "position": [9999990.0, 0.0, 0.0],
          "rotation": [0.0, 0.0, 0.0, 1.0],
          "scale": [2.0, 2.0, 2.0]
        }
      }
    },
    {
      "components": {
        "Name": {
          "name": "Ground Plane"
        },
        "MeshId": {
          "0": "Plane"
        },
        "Material": {
          "color": [0.5, 0.5, 0.5, 1.0]
        },
        "WorldTransform": {
          "position": [10000000.0, -5.0, 0.0],
          "rotation": [0.0, 0.0, 0.0, 1.0],
          "scale": [50.0, 1.0, 50.0]
        }
      }
    }
  ]
}